media_muncher/__init__.py
media_muncher/analysers/__init__.py
media_muncher/analysers/dash.py
media_muncher/analysers/hls.py
media_muncher/analysers/hls_compare.py
media_muncher/cast.py
media_muncher/codecstrings.py
media_muncher/exceptions.py
media_muncher/format.py
media_muncher/framerate.py
media_muncher/gop_size.py
media_muncher/h264_levels.py
media_muncher/handlers/__init__.py
media_muncher/handlers/dash.py
media_muncher/handlers/factory.py
media_muncher/handlers/generic.py
media_muncher/handlers/hls.py
media_muncher/handlers/jpeg.py
media_muncher/handlers/mp4.py
media_muncher/handlers/png.py
media_muncher/handlers/vast.py
media_muncher/handlers/vmap.py
media_muncher/handlers/xml.py
media_muncher/messages.py
media_muncher/models/timeline_models.py
media_muncher/profile/__init__.py
media_muncher/profile/factory.py
media_muncher/profile/generator.py
media_muncher/profile/schemas/base.py
media_muncher/profile/schemas/bkt_v1.py
media_muncher/profile/schemas/bkt_v2.py
media_muncher/profile/schemas/bkt_v2_1.py
media_muncher/resolution.py
media_muncher/segment_size.py
media_muncher-2.0.0.dist-info/METADATA
media_muncher-2.0.0.dist-info/WHEEL
media_muncher-2.0.0.dist-info/licenses/LICENSE.md
media_muncher-2.0.0.dist-info/RECORD
