Metadata-Version: 2.4
Name: media-muncher
Version: 2.0.0
Summary: A module to work with media assets, in particular DASH and HLS streams
License: MIT
License-File: LICENSE.md
Author: Fabre Lambeau
Author-email: fabre.lambeau@broadpeak.tv
Requires-Python: >=3.10,<3.14
Classifier: License :: OSI Approved :: MIT License
Classifier: Programming Language :: Python :: 3
Classifier: Programming Language :: Python :: 3.10
Classifier: Programming Language :: Python :: 3.11
Classifier: Programming Language :: Python :: 3.12
Classifier: Programming Language :: Python :: 3.13
Requires-Dist: isodate (>=0.6.1,<0.7.0)
Requires-Dist: loguru (>=0.7.2,<0.8.0)
Requires-Dist: lxml (>=5.2.2,<6.0.0)
Requires-Dist: m3u8 (>=4.1.0,<5.0.0)
Requires-Dist: mpd-inspector (>=1.2.1,<2.0.0)
Requires-Dist: pymediainfo (>=7.0.0,<8.0.0)
Requires-Dist: requests (>=2.32.5,<3.0.0)
